cloudzeta_sdk.libs/libIex-3_1.so
cloudzeta_sdk.libs/libIex-3_1.so.30
cloudzeta_sdk.libs/libIex-3_1.so.30.11.1
cloudzeta_sdk.libs/libIex.so
cloudzeta_sdk.libs/libIlmThread-3_1.so
cloudzeta_sdk.libs/libIlmThread-3_1.so.30
cloudzeta_sdk.libs/libIlmThread-3_1.so.30.11.1
cloudzeta_sdk.libs/libIlmThread.so
cloudzeta_sdk.libs/libImath-3_1.so
cloudzeta_sdk.libs/libImath-3_1.so.29
cloudzeta_sdk.libs/libImath-3_1.so.29.8.0
cloudzeta_sdk.libs/libImath.so
cloudzeta_sdk.libs/libMaterialXCore.so
cloudzeta_sdk.libs/libMaterialXCore.so.1
cloudzeta_sdk.libs/libMaterialXCore.so.1.38.8
cloudzeta_sdk.libs/libMaterialXFormat.so
cloudzeta_sdk.libs/libMaterialXFormat.so.1
cloudzeta_sdk.libs/libMaterialXFormat.so.1.38.8
cloudzeta_sdk.libs/libMaterialXGenGlsl.so
cloudzeta_sdk.libs/libMaterialXGenGlsl.so.1
cloudzeta_sdk.libs/libMaterialXGenGlsl.so.1.38.8
cloudzeta_sdk.libs/libMaterialXGenMdl.so
cloudzeta_sdk.libs/libMaterialXGenMdl.so.1
cloudzeta_sdk.libs/libMaterialXGenMdl.so.1.38.8
cloudzeta_sdk.libs/libMaterialXGenMsl.so
cloudzeta_sdk.libs/libMaterialXGenMsl.so.1
cloudzeta_sdk.libs/libMaterialXGenMsl.so.1.38.8
cloudzeta_sdk.libs/libMaterialXGenOsl.so
cloudzeta_sdk.libs/libMaterialXGenOsl.so.1
cloudzeta_sdk.libs/libMaterialXGenOsl.so.1.38.8
cloudzeta_sdk.libs/libMaterialXGenShader.so
cloudzeta_sdk.libs/libMaterialXGenShader.so.1
cloudzeta_sdk.libs/libMaterialXGenShader.so.1.38.8
cloudzeta_sdk.libs/libMaterialXRender.so
cloudzeta_sdk.libs/libMaterialXRender.so.1
cloudzeta_sdk.libs/libMaterialXRender.so.1.38.8
cloudzeta_sdk.libs/libMaterialXRenderGlsl.so
cloudzeta_sdk.libs/libMaterialXRenderGlsl.so.1
cloudzeta_sdk.libs/libMaterialXRenderGlsl.so.1.38.8
cloudzeta_sdk.libs/libMaterialXRenderHw.so
cloudzeta_sdk.libs/libMaterialXRenderHw.so.1
cloudzeta_sdk.libs/libMaterialXRenderHw.so.1.38.8
cloudzeta_sdk.libs/libMaterialXRenderOsl.so
cloudzeta_sdk.libs/libMaterialXRenderOsl.so.1
cloudzeta_sdk.libs/libMaterialXRenderOsl.so.1.38.8
cloudzeta_sdk.libs/libOpenEXR-3_1.so
cloudzeta_sdk-0.11.348.dist-info/METADATA
cloudzeta_sdk-0.11.348.dist-info/WHEEL
cloudzeta_sdk-0.11.348.dist-info/top_level.txt
cloudzeta_sdk-0.11.348.dist-info/RECORD
