Metadata-Version: 2.1
Name: cloudzeta-sdk
Version: 0.11.348
Summary: UNKNOWN
Home-page: https://cloudzeta.com
Author: Zeta Computing, Inc.
Author-email: dev@cloudzeta.com
License: UNKNOWN
Project-URL: Documentation, https://docs.cloudzeta.com
Project-URL: Source, https://github.com/cloud-zeta/zeta-samples
Project-URL: Issue Tracker, https://github.com/cloud-zeta/zeta-samples/issues
Project-URL: Discussion Group, https://discord.gg/kyTzU2rxYN
Platform: UNKNOWN
Classifier: Development Status :: 4 - Beta
Classifier: Programming Language :: Python :: 3
Classifier: Operating System :: POSIX :: Linux
Classifier: Topic :: Multimedia :: Graphics
Requires-Python: >=3.7, <3.12
Requires-Dist: cryptography >=3.4.8
Requires-Dist: google-cloud-firestore >=2.14.0
Requires-Dist: supabase >=2.9.1
